cs_flickrgallery/__init__.py
cs_flickrgallery/configure.zcml
cs_flickrgallery/dependencies.zcml
cs_flickrgallery/interfaces.py
cs_flickrgallery/permissions.zcml
cs_flickrgallery/profiles.zcml
cs_flickrgallery/testing.py
cs_flickrgallery/utils.py
cs_flickrgallery/behaviors/__init__.py
cs_flickrgallery/behaviors/configure.zcml
cs_flickrgallery/behaviors/flickr_gallery.py
cs_flickrgallery/content/__init__.py
cs_flickrgallery/controlpanels/__init__.py
cs_flickrgallery/controlpanels/configure.zcml
cs_flickrgallery/controlpanels/controlpanel.py
cs_flickrgallery/indexers/__init__.py
cs_flickrgallery/indexers/configure.zcml
cs_flickrgallery/locales/__init__.py
cs_flickrgallery/locales/__main__.py
cs_flickrgallery/locales/cs_flickrgallery.pot
cs_flickrgallery/locales/en/LC_MESSAGES/cs_flickrgallery.mo
cs_flickrgallery/locales/en/LC_MESSAGES/cs_flickrgallery.po
cs_flickrgallery/locales/es/LC_MESSAGES/cs_flickrgallery.mo
cs_flickrgallery/locales/es/LC_MESSAGES/cs_flickrgallery.po
cs_flickrgallery/locales/eu/LC_MESSAGES/cs_flickrgallery.mo
cs_flickrgallery/locales/eu/LC_MESSAGES/cs_flickrgallery.po
cs_flickrgallery/profiles/default/browserlayer.xml
cs_flickrgallery/profiles/default/catalog.xml
cs_flickrgallery/profiles/default/controlpanel.xml
cs_flickrgallery/profiles/default/diff_tool.xml
cs_flickrgallery/profiles/default/metadata.xml
cs_flickrgallery/profiles/default/repositorytool.xml
cs_flickrgallery/profiles/default/rolemap.xml
cs_flickrgallery/profiles/default/types.xml
cs_flickrgallery/profiles/default/registry/main.xml
cs_flickrgallery/profiles/default/types/.gitkeep
cs_flickrgallery/profiles/uninstall/browserlayer.xml
cs_flickrgallery/profiles/uninstall/controlpanel.xml
cs_flickrgallery/profiles/uninstall/registry.xml
cs_flickrgallery/scripts/__init__.py
cs_flickrgallery/scripts/import_photos_from_flickr.py
cs_flickrgallery/scripts/utils.py
cs_flickrgallery/setuphandlers/__init__.py
cs_flickrgallery/upgrades/__init__.py
cs_flickrgallery/upgrades/configure.zcml
cs_flickrgallery-1.2.dist-info/METADATA
cs_flickrgallery-1.2.dist-info/WHEEL
cs_flickrgallery-1.2.dist-info/entry_points.txt
cs_flickrgallery-1.2.dist-info/licenses/LICENSE.GPL
cs_flickrgallery-1.2.dist-info/licenses/LICENSE.md
cs_flickrgallery-1.2.dist-info/RECORD
