Metadata-Version: 2.4
Name: cs_flickrgallery
Version: 1.2
Summary: A new addon for Plone
Project-URL: Homepage, https://github.com/codesyntax/cs_flickrgallery
Project-URL: PyPI, https://pypi.org/project/cs_flickrgallery
Project-URL: Source, https://github.com/codesyntax/cs_flickrgallery
Project-URL: Tracker, https://github.com/codesyntax/cs_flickrgallery/issues
Author-email: Mikel Larreategi <mlarreategi@codesyntax.com>
License-File: LICENSE.GPL
License-File: LICENSE.md
Keywords: CMS,Plone,Python
Classifier: Development Status :: 3 - Alpha
Classifier: Environment :: Web Environment
Classifier: Framework :: Plone
Classifier: Framework :: Plone :: 6.0
Classifier: Framework :: Plone :: 6.1
Classifier: Framework :: Plone :: Addon
Classifier: License :: OSI Approved :: GNU General Public License v2 (GPLv2)
Classifier: Operating System :: OS Independent
Classifier: Programming Language :: Python
Classifier: Programming Language :: Python :: 3.10
Classifier: Programming Language :: Python :: 3.11
Classifier: Programming Language :: Python :: 3.12
Classifier: Programming Language :: Python :: 3.13
Requires-Python: >=3.10
Requires-Dist: flickrapi
Requires-Dist: plone-api
Requires-Dist: products-cmfplone
Provides-Extra: test
Requires-Dist: horse-with-no-namespace; extra == 'test'
Requires-Dist: plone-app-testing; extra == 'test'
Requires-Dist: plone-classicui; extra == 'test'
Requires-Dist: plone-restapi[test]; extra == 'test'
Requires-Dist: pytest; extra == 'test'
Requires-Dist: pytest-cov; extra == 'test'
Requires-Dist: pytest-plone>=0.5.0; extra == 'test'
